{
  "overall_accuracy": 0.282,
  "task_classes": {
    "0": [
      "plane",
      "frog"
    ],
    "1": [
      "deer",
      "dog"
    ],
    "2": [
      "horse",
      "bird"
    ],
    "3": [
      "car",
      "cat"
    ],
    "4": [
      "truck",
      "ship"
    ]
  },
  "per_class_stats": {
    "plane": {
      "real_total": 1000,
      "true_positives": 256,
      "false_negative": 744,
      "false_positive": 242
    },
    "car": {
      "real_total": 1000,
      "true_positives": 980,
      "false_negative": 20,
      "false_positive": 3476
    },
    "bird": {
      "real_total": 1000,
      "true_positives": 39,
      "false_negative": 961,
      "false_positive": 79
    },
    "cat": {
      "real_total": 1000,
      "true_positives": 704,
      "false_negative": 296,
      "false_positive": 2395
    },
    "deer": {
      "real_total": 1000,
      "true_positives": 85,
      "false_negative": 915,
      "false_positive": 101
    },
    "dog": {
      "real_total": 1000,
      "true_positives": 0,
      "false_negative": 1000,
      "false_positive": 0
    },
    "frog": {
      "real_total": 1000,
      "true_positives": 337,
      "false_negative": 663,
      "false_positive": 408
    },
    "horse": {
      "real_total": 1000,
      "true_positives": 419,
      "false_negative": 581,
      "false_positive": 478
    },
    "ship": {
      "real_total": 1000,
      "true_positives": 0,
      "false_negative": 1000,
      "false_positive": 0
    },
    "truck": {
      "real_total": 1000,
      "true_positives": 0,
      "false_negative": 1000,
      "false_positive": 1
    }
  },
  "per_class_accuracy": {
    "plane": 0.256,
    "car": 0.98,
    "bird": 0.039,
    "cat": 0.704,
    "deer": 0.085,
    "dog": 0.0,
    "frog": 0.337,
    "horse": 0.419,
    "ship": 0.0,
    "truck": 0.0
  },
  "per_task_accuracy": {
    "0": 0.2965,
    "1": 0.0425,
    "2": 0.22899999999999998,
    "3": 0.842,
    "4": 0.0
  }
}