{
  "overall_accuracy": 0.1202,
  "task_classes": {
    "0": [
      "television",
      "orange",
      "rose",
      "willow_tree",
      "crab",
      "fox",
      "apple",
      "cup",
      "clock",
      "possum",
      "shrew",
      "cloud",
      "telephone",
      "hamster",
      "poppy",
      "can",
      "girl",
      "caterpillar",
      "cattle",
      "maple_tree"
    ],
    "1": [
      "raccoon",
      "rabbit",
      "bee",
      "lamp",
      "lawn_mower",
      "mountain",
      "shark",
      "boy",
      "sweet_pepper",
      "bus",
      "crocodile",
      "snail",
      "turtle",
      "lion",
      "chair",
      "squirrel",
      "porcupine",
      "pickup_truck",
      "bowl",
      "trout"
    ],
    "2": [
      "worm",
      "plate",
      "motorcycle",
      "ray",
      "table",
      "bear",
      "streetcar",
      "palm_tree",
      "orchid",
      "road",
      "butterfly",
      "wardrobe",
      "mouse",
      "man",
      "whale",
      "bottle",
      "mushroom",
      "pine_tree",
      "pear",
      "dolphin"
    ],
    "3": [
      "house",
      "couch",
      "bridge",
      "snake",
      "plain",
      "keyboard",
      "rocket",
      "chimpanzee",
      "sea",
      "oak_tree",
      "otter",
      "skunk",
      "tank",
      "bed",
      "wolf",
      "skyscraper",
      "beetle",
      "kangaroo",
      "camel",
      "woman"
    ],
    "4": [
      "lizard",
      "tulip",
      "spider",
      "forest",
      "dinosaur",
      "castle",
      "bicycle",
      "flatfish",
      "lobster",
      "train",
      "baby",
      "tiger",
      "cockroach",
      "leopard",
      "elephant",
      "tractor",
      "sunflower",
      "aquarium_fish",
      "beaver",
      "seal"
    ]
  },
  "per_class_stats": {
    "apple": {
      "real_total": 100,
      "true_positives": 18,
      "false_negative": 82,
      "false_positive": 52
    },
    "aquarium_fish": {
      "real_total": 100,
      "true_positives": 3,
      "false_negative": 97,
      "false_positive": 28
    },
    "baby": {
      "real_total": 100,
      "true_positives": 11,
      "false_negative": 89,
      "false_positive": 70
    },
    "bear": {
      "real_total": 100,
      "true_positives": 6,
      "false_negative": 94,
      "false_positive": 48
    },
    "beaver": {
      "real_total": 100,
      "true_positives": 2,
      "false_negative": 98,
      "false_positive": 39
    },
    "bed": {
      "real_total": 100,
      "true_positives": 4,
      "false_negative": 96,
      "false_positive": 65
    },
    "bee": {
      "real_total": 100,
      "true_positives": 2,
      "false_negative": 98,
      "false_positive": 85
    },
    "beetle": {
      "real_total": 100,
      "true_positives": 1,
      "false_negative": 99,
      "false_positive": 5
    },
    "bicycle": {
      "real_total": 100,
      "true_positives": 4,
      "false_negative": 96,
      "false_positive": 98
    },
    "bottle": {
      "real_total": 100,
      "true_positives": 9,
      "false_negative": 91,
      "false_positive": 65
    },
    "bowl": {
      "real_total": 100,
      "true_positives": 0,
      "false_negative": 100,
      "false_positive": 13
    },
    "boy": {
      "real_total": 100,
      "true_positives": 2,
      "false_negative": 98,
      "false_positive": 68
    },
    "bridge": {
      "real_total": 100,
      "true_positives": 9,
      "false_negative": 91,
      "false_positive": 111
    },
    "bus": {
      "real_total": 100,
      "true_positives": 0,
      "false_negative": 100,
      "false_positive": 5
    },
    "butterfly": {
      "real_total": 100,
      "true_positives": 8,
      "false_negative": 92,
      "false_positive": 103
    },
    "camel": {
      "real_total": 100,
      "true_positives": 3,
      "false_negative": 97,
      "false_positive": 26
    },
    "can": {
      "real_total": 100,
      "true_positives": 0,
      "false_negative": 100,
      "false_positive": 10
    },
    "castle": {
      "real_total": 100,
      "true_positives": 37,
      "false_negative": 63,
      "false_positive": 194
    },
    "caterpillar": {
      "real_total": 100,
      "true_positives": 16,
      "false_negative": 84,
      "false_positive": 178
    },
    "cattle": {
      "real_total": 100,
      "true_positives": 4,
      "false_negative": 96,
      "false_positive": 40
    },
    "chair": {
      "real_total": 100,
      "true_positives": 53,
      "false_negative": 47,
      "false_positive": 905
    },
    "chimpanzee": {
      "real_total": 100,
      "true_positives": 25,
      "false_negative": 75,
      "false_positive": 37
    },
    "clock": {
      "real_total": 100,
      "true_positives": 5,
      "false_negative": 95,
      "false_positive": 74
    },
    "cloud": {
      "real_total": 100,
      "true_positives": 21,
      "false_negative": 79,
      "false_positive": 157
    },
    "cockroach": {
      "real_total": 100,
      "true_positives": 55,
      "false_negative": 45,
      "false_positive": 226
    },
    "couch": {
      "real_total": 100,
      "true_positives": 2,
      "false_negative": 98,
      "false_positive": 27
    },
    "crab": {
      "real_total": 100,
      "true_positives": 1,
      "false_negative": 99,
      "false_positive": 55
    },
    "crocodile": {
      "real_total": 100,
      "true_positives": 8,
      "false_negative": 92,
      "false_positive": 65
    },
    "cup": {
      "real_total": 100,
      "true_positives": 2,
      "false_negative": 98,
      "false_positive": 52
    },
    "dinosaur": {
      "real_total": 100,
      "true_positives": 5,
      "false_negative": 95,
      "false_positive": 42
    },
    "dolphin": {
      "real_total": 100,
      "true_positives": 7,
      "false_negative": 93,
      "false_positive": 20
    },
    "elephant": {
      "real_total": 100,
      "true_positives": 1,
      "false_negative": 99,
      "false_positive": 0
    },
    "flatfish": {
      "real_total": 100,
      "true_positives": 2,
      "false_negative": 98,
      "false_positive": 10
    },
    "forest": {
      "real_total": 100,
      "true_positives": 14,
      "false_negative": 86,
      "false_positive": 118
    },
    "fox": {
      "real_total": 100,
      "true_positives": 8,
      "false_negative": 92,
      "false_positive": 79
    },
    "girl": {
      "real_total": 100,
      "true_positives": 8,
      "false_negative": 92,
      "false_positive": 46
    },
    "hamster": {
      "real_total": 100,
      "true_positives": 18,
      "false_negative": 82,
      "false_positive": 153
    },
    "house": {
      "real_total": 100,
      "true_positives": 28,
      "false_negative": 72,
      "false_positive": 200
    },
    "kangaroo": {
      "real_total": 100,
      "true_positives": 4,
      "false_negative": 96,
      "false_positive": 50
    },
    "keyboard": {
      "real_total": 100,
      "true_positives": 12,
      "false_negative": 88,
      "false_positive": 181
    },
    "lamp": {
      "real_total": 100,
      "true_positives": 1,
      "false_negative": 99,
      "false_positive": 25
    },
    "lawn_mower": {
      "real_total": 100,
      "true_positives": 8,
      "false_negative": 92,
      "false_positive": 18
    },
    "leopard": {
      "real_total": 100,
      "true_positives": 3,
      "false_negative": 97,
      "false_positive": 44
    },
    "lion": {
      "real_total": 100,
      "true_positives": 19,
      "false_negative": 81,
      "false_positive": 116
    },
    "lizard": {
      "real_total": 100,
      "true_positives": 0,
      "false_negative": 100,
      "false_positive": 71
    },
    "lobster": {
      "real_total": 100,
      "true_positives": 0,
      "false_negative": 100,
      "false_positive": 28
    },
    "man": {
      "real_total": 100,
      "true_positives": 14,
      "false_negative": 86,
      "false_positive": 85
    },
    "maple_tree": {
      "real_total": 100,
      "true_positives": 15,
      "false_negative": 85,
      "false_positive": 92
    },
    "motorcycle": {
      "real_total": 100,
      "true_positives": 28,
      "false_negative": 72,
      "false_positive": 126
    },
    "mountain": {
      "real_total": 100,
      "true_positives": 2,
      "false_negative": 98,
      "false_positive": 52
    },
    "mouse": {
      "real_total": 100,
      "true_positives": 4,
      "false_negative": 96,
      "false_positive": 75
    },
    "mushroom": {
      "real_total": 100,
      "true_positives": 3,
      "false_negative": 97,
      "false_positive": 49
    },
    "oak_tree": {
      "real_total": 100,
      "true_positives": 32,
      "false_negative": 68,
      "false_positive": 116
    },
    "orange": {
      "real_total": 100,
      "true_positives": 74,
      "false_negative": 26,
      "false_positive": 243
    },
    "orchid": {
      "real_total": 100,
      "true_positives": 22,
      "false_negative": 78,
      "false_positive": 59
    },
    "otter": {
      "real_total": 100,
      "true_positives": 1,
      "false_negative": 99,
      "false_positive": 48
    },
    "palm_tree": {
      "real_total": 100,
      "true_positives": 11,
      "false_negative": 89,
      "false_positive": 36
    },
    "pear": {
      "real_total": 100,
      "true_positives": 18,
      "false_negative": 82,
      "false_positive": 161
    },
    "pickup_truck": {
      "real_total": 100,
      "true_positives": 5,
      "false_negative": 95,
      "false_positive": 42
    },
    "pine_tree": {
      "real_total": 100,
      "true_positives": 5,
      "false_negative": 95,
      "false_positive": 35
    },
    "plain": {
      "real_total": 100,
      "true_positives": 40,
      "false_negative": 60,
      "false_positive": 108
    },
    "plate": {
      "real_total": 100,
      "true_positives": 14,
      "false_negative": 86,
      "false_positive": 212
    },
    "poppy": {
      "real_total": 100,
      "true_positives": 21,
      "false_negative": 79,
      "false_positive": 117
    },
    "porcupine": {
      "real_total": 100,
      "true_positives": 7,
      "false_negative": 93,
      "false_positive": 28
    },
    "possum": {
      "real_total": 100,
      "true_positives": 3,
      "false_negative": 97,
      "false_positive": 41
    },
    "rabbit": {
      "real_total": 100,
      "true_positives": 5,
      "false_negative": 95,
      "false_positive": 160
    },
    "raccoon": {
      "real_total": 100,
      "true_positives": 2,
      "false_negative": 98,
      "false_positive": 61
    },
    "ray": {
      "real_total": 100,
      "true_positives": 15,
      "false_negative": 85,
      "false_positive": 24
    },
    "road": {
      "real_total": 100,
      "true_positives": 32,
      "false_negative": 68,
      "false_positive": 71
    },
    "rocket": {
      "real_total": 100,
      "true_positives": 16,
      "false_negative": 84,
      "false_positive": 102
    },
    "rose": {
      "real_total": 100,
      "true_positives": 21,
      "false_negative": 79,
      "false_positive": 71
    },
    "sea": {
      "real_total": 100,
      "true_positives": 31,
      "false_negative": 69,
      "false_positive": 93
    },
    "seal": {
      "real_total": 100,
      "true_positives": 3,
      "false_negative": 97,
      "false_positive": 85
    },
    "shark": {
      "real_total": 100,
      "true_positives": 20,
      "false_negative": 80,
      "false_positive": 235
    },
    "shrew": {
      "real_total": 100,
      "true_positives": 0,
      "false_negative": 100,
      "false_positive": 1
    },
    "skunk": {
      "real_total": 100,
      "true_positives": 26,
      "false_negative": 74,
      "false_positive": 31
    },
    "skyscraper": {
      "real_total": 100,
      "true_positives": 19,
      "false_negative": 81,
      "false_positive": 76
    },
    "snail": {
      "real_total": 100,
      "true_positives": 5,
      "false_negative": 95,
      "false_positive": 90
    },
    "snake": {
      "real_total": 100,
      "true_positives": 2,
      "false_negative": 98,
      "false_positive": 82
    },
    "spider": {
      "real_total": 100,
      "true_positives": 2,
      "false_negative": 98,
      "false_positive": 38
    },
    "squirrel": {
      "real_total": 100,
      "true_positives": 5,
      "false_negative": 95,
      "false_positive": 134
    },
    "streetcar": {
      "real_total": 100,
      "true_positives": 1,
      "false_negative": 99,
      "false_positive": 43
    },
    "sunflower": {
      "real_total": 100,
      "true_positives": 52,
      "false_negative": 48,
      "false_positive": 67
    },
    "sweet_pepper": {
      "real_total": 100,
      "true_positives": 7,
      "false_negative": 93,
      "false_positive": 42
    },
    "table": {
      "real_total": 100,
      "true_positives": 1,
      "false_negative": 99,
      "false_positive": 43
    },
    "tank": {
      "real_total": 100,
      "true_positives": 2,
      "false_negative": 98,
      "false_positive": 15
    },
    "telephone": {
      "real_total": 100,
      "true_positives": 24,
      "false_negative": 76,
      "false_positive": 148
    },
    "television": {
      "real_total": 100,
      "true_positives": 13,
      "false_negative": 87,
      "false_positive": 203
    },
    "tiger": {
      "real_total": 100,
      "true_positives": 11,
      "false_negative": 89,
      "false_positive": 213
    },
    "tractor": {
      "real_total": 100,
      "true_positives": 1,
      "false_negative": 99,
      "false_positive": 32
    },
    "train": {
      "real_total": 100,
      "true_positives": 1,
      "false_negative": 99,
      "false_positive": 16
    },
    "trout": {
      "real_total": 100,
      "true_positives": 3,
      "false_negative": 97,
      "false_positive": 45
    },
    "tulip": {
      "real_total": 100,
      "true_positives": 6,
      "false_negative": 94,
      "false_positive": 88
    },
    "turtle": {
      "real_total": 100,
      "true_positives": 14,
      "false_negative": 86,
      "false_positive": 129
    },
    "wardrobe": {
      "real_total": 100,
      "true_positives": 13,
      "false_negative": 87,
      "false_positive": 48
    },
    "whale": {
      "real_total": 100,
      "true_positives": 42,
      "false_negative": 58,
      "false_positive": 166
    },
    "willow_tree": {
      "real_total": 100,
      "true_positives": 29,
      "false_negative": 71,
      "false_positive": 155
    },
    "wolf": {
      "real_total": 100,
      "true_positives": 4,
      "false_negative": 96,
      "false_positive": 26
    },
    "woman": {
      "real_total": 100,
      "true_positives": 3,
      "false_negative": 97,
      "false_positive": 38
    },
    "worm": {
      "real_total": 100,
      "true_positives": 3,
      "false_negative": 97,
      "false_positive": 100
    }
  },
  "per_class_accuracy": {
    "apple": 0.18,
    "aquarium_fish": 0.03,
    "baby": 0.11,
    "bear": 0.06,
    "beaver": 0.02,
    "bed": 0.04,
    "bee": 0.02,
    "beetle": 0.01,
    "bicycle": 0.04,
    "bottle": 0.09,
    "bowl": 0.0,
    "boy": 0.02,
    "bridge": 0.09,
    "bus": 0.0,
    "butterfly": 0.08,
    "camel": 0.03,
    "can": 0.0,
    "castle": 0.37,
    "caterpillar": 0.16,
    "cattle": 0.04,
    "chair": 0.53,
    "chimpanzee": 0.25,
    "clock": 0.05,
    "cloud": 0.21,
    "cockroach": 0.55,
    "couch": 0.02,
    "crab": 0.01,
    "crocodile": 0.08,
    "cup": 0.02,
    "dinosaur": 0.05,
    "dolphin": 0.07,
    "elephant": 0.01,
    "flatfish": 0.02,
    "forest": 0.14,
    "fox": 0.08,
    "girl": 0.08,
    "hamster": 0.18,
    "house": 0.28,
    "kangaroo": 0.04,
    "keyboard": 0.12,
    "lamp": 0.01,
    "lawn_mower": 0.08,
    "leopard": 0.03,
    "lion": 0.19,
    "lizard": 0.0,
    "lobster": 0.0,
    "man": 0.14,
    "maple_tree": 0.15,
    "motorcycle": 0.28,
    "mountain": 0.02,
    "mouse": 0.04,
    "mushroom": 0.03,
    "oak_tree": 0.32,
    "orange": 0.74,
    "orchid": 0.22,
    "otter": 0.01,
    "palm_tree": 0.11,
    "pear": 0.18,
    "pickup_truck": 0.05,
    "pine_tree": 0.05,
    "plain": 0.4,
    "plate": 0.14,
    "poppy": 0.21,
    "porcupine": 0.07,
    "possum": 0.03,
    "rabbit": 0.05,
    "raccoon": 0.02,
    "ray": 0.15,
    "road": 0.32,
    "rocket": 0.16,
    "rose": 0.21,
    "sea": 0.31,
    "seal": 0.03,
    "shark": 0.2,
    "shrew": 0.0,
    "skunk": 0.26,
    "skyscraper": 0.19,
    "snail": 0.05,
    "snake": 0.02,
    "spider": 0.02,
    "squirrel": 0.05,
    "streetcar": 0.01,
    "sunflower": 0.52,
    "sweet_pepper": 0.07,
    "table": 0.01,
    "tank": 0.02,
    "telephone": 0.24,
    "television": 0.13,
    "tiger": 0.11,
    "tractor": 0.01,
    "train": 0.01,
    "trout": 0.03,
    "tulip": 0.06,
    "turtle": 0.14,
    "wardrobe": 0.13,
    "whale": 0.42,
    "willow_tree": 0.29,
    "wolf": 0.04,
    "woman": 0.03,
    "worm": 0.03
  },
  "per_task_accuracy": {
    "0": 0.15050000000000002,
    "1": 0.08400000000000002,
    "2": 0.128,
    "3": 0.13199999999999998,
    "4": 0.10649999999999997
  }
}