{
  "overall_accuracy": 0.0644,
  "task_classes": {
    "0": [
      "cattle",
      "lamp",
      "pickup_truck",
      "pear",
      "whale",
      "orange",
      "snail",
      "dolphin",
      "tractor",
      "sea",
      "bridge",
      "ray",
      "lawn_mower",
      "beaver",
      "baby",
      "bear",
      "castle",
      "cup",
      "mushroom",
      "otter"
    ],
    "1": [
      "rabbit",
      "skyscraper",
      "table",
      "woman",
      "lobster",
      "couch",
      "beetle",
      "maple_tree",
      "rose",
      "worm",
      "chimpanzee",
      "seal",
      "tank",
      "plain",
      "bee",
      "shrew",
      "willow_tree",
      "mouse",
      "mountain",
      "squirrel"
    ],
    "2": [
      "kangaroo",
      "turtle",
      "dinosaur",
      "hamster",
      "bicycle",
      "motorcycle",
      "bed",
      "shark",
      "house",
      "chair",
      "wardrobe",
      "camel",
      "cloud",
      "skunk",
      "can",
      "train",
      "orchid",
      "bowl",
      "keyboard",
      "snake"
    ],
    "3": [
      "plate",
      "bottle",
      "boy",
      "lizard",
      "television",
      "apple",
      "wolf",
      "caterpillar",
      "butterfly",
      "pine_tree",
      "rocket",
      "poppy",
      "tulip",
      "crab",
      "possum",
      "porcupine",
      "streetcar",
      "clock",
      "sunflower",
      "lion"
    ],
    "4": [
      "aquarium_fish",
      "crocodile",
      "bus",
      "telephone",
      "fox",
      "tiger",
      "leopard",
      "girl",
      "oak_tree",
      "flatfish",
      "spider",
      "forest",
      "palm_tree",
      "man",
      "cockroach",
      "elephant",
      "trout",
      "raccoon",
      "road",
      "sweet_pepper"
    ]
  },
  "per_class_stats": {
    "apple": {
      "real_total": 100,
      "true_positives": 28,
      "false_negative": 72,
      "false_positive": 155
    },
    "aquarium_fish": {
      "real_total": 100,
      "true_positives": 0,
      "false_negative": 100,
      "false_positive": 0
    },
    "baby": {
      "real_total": 100,
      "true_positives": 1,
      "false_negative": 99,
      "false_positive": 64
    },
    "bear": {
      "real_total": 100,
      "true_positives": 2,
      "false_negative": 98,
      "false_positive": 13
    },
    "beaver": {
      "real_total": 100,
      "true_positives": 1,
      "false_negative": 99,
      "false_positive": 30
    },
    "bed": {
      "real_total": 100,
      "true_positives": 2,
      "false_negative": 98,
      "false_positive": 20
    },
    "bee": {
      "real_total": 100,
      "true_positives": 2,
      "false_negative": 98,
      "false_positive": 119
    },
    "beetle": {
      "real_total": 100,
      "true_positives": 3,
      "false_negative": 97,
      "false_positive": 175
    },
    "bicycle": {
      "real_total": 100,
      "true_positives": 8,
      "false_negative": 92,
      "false_positive": 98
    },
    "bottle": {
      "real_total": 100,
      "true_positives": 4,
      "false_negative": 96,
      "false_positive": 37
    },
    "bowl": {
      "real_total": 100,
      "true_positives": 2,
      "false_negative": 98,
      "false_positive": 156
    },
    "boy": {
      "real_total": 100,
      "true_positives": 11,
      "false_negative": 89,
      "false_positive": 232
    },
    "bridge": {
      "real_total": 100,
      "true_positives": 12,
      "false_negative": 88,
      "false_positive": 130
    },
    "bus": {
      "real_total": 100,
      "true_positives": 0,
      "false_negative": 100,
      "false_positive": 0
    },
    "butterfly": {
      "real_total": 100,
      "true_positives": 4,
      "false_negative": 96,
      "false_positive": 258
    },
    "camel": {
      "real_total": 100,
      "true_positives": 13,
      "false_negative": 87,
      "false_positive": 180
    },
    "can": {
      "real_total": 100,
      "true_positives": 10,
      "false_negative": 90,
      "false_positive": 117
    },
    "castle": {
      "real_total": 100,
      "true_positives": 3,
      "false_negative": 97,
      "false_positive": 107
    },
    "caterpillar": {
      "real_total": 100,
      "true_positives": 13,
      "false_negative": 87,
      "false_positive": 89
    },
    "cattle": {
      "real_total": 100,
      "true_positives": 8,
      "false_negative": 92,
      "false_positive": 58
    },
    "chair": {
      "real_total": 100,
      "true_positives": 18,
      "false_negative": 82,
      "false_positive": 41
    },
    "chimpanzee": {
      "real_total": 100,
      "true_positives": 5,
      "false_negative": 95,
      "false_positive": 44
    },
    "clock": {
      "real_total": 100,
      "true_positives": 2,
      "false_negative": 98,
      "false_positive": 102
    },
    "cloud": {
      "real_total": 100,
      "true_positives": 17,
      "false_negative": 83,
      "false_positive": 73
    },
    "cockroach": {
      "real_total": 100,
      "true_positives": 0,
      "false_negative": 100,
      "false_positive": 0
    },
    "couch": {
      "real_total": 100,
      "true_positives": 3,
      "false_negative": 97,
      "false_positive": 122
    },
    "crab": {
      "real_total": 100,
      "true_positives": 1,
      "false_negative": 99,
      "false_positive": 57
    },
    "crocodile": {
      "real_total": 100,
      "true_positives": 0,
      "false_negative": 100,
      "false_positive": 0
    },
    "cup": {
      "real_total": 100,
      "true_positives": 6,
      "false_negative": 94,
      "false_positive": 24
    },
    "dinosaur": {
      "real_total": 100,
      "true_positives": 2,
      "false_negative": 98,
      "false_positive": 124
    },
    "dolphin": {
      "real_total": 100,
      "true_positives": 3,
      "false_negative": 97,
      "false_positive": 32
    },
    "elephant": {
      "real_total": 100,
      "true_positives": 0,
      "false_negative": 100,
      "false_positive": 0
    },
    "flatfish": {
      "real_total": 100,
      "true_positives": 0,
      "false_negative": 100,
      "false_positive": 0
    },
    "forest": {
      "real_total": 100,
      "true_positives": 0,
      "false_negative": 100,
      "false_positive": 0
    },
    "fox": {
      "real_total": 100,
      "true_positives": 0,
      "false_negative": 100,
      "false_positive": 0
    },
    "girl": {
      "real_total": 100,
      "true_positives": 0,
      "false_negative": 100,
      "false_positive": 0
    },
    "hamster": {
      "real_total": 100,
      "true_positives": 2,
      "false_negative": 98,
      "false_positive": 59
    },
    "house": {
      "real_total": 100,
      "true_positives": 6,
      "false_negative": 94,
      "false_positive": 103
    },
    "kangaroo": {
      "real_total": 100,
      "true_positives": 7,
      "false_negative": 93,
      "false_positive": 174
    },
    "keyboard": {
      "real_total": 100,
      "true_positives": 1,
      "false_negative": 99,
      "false_positive": 123
    },
    "lamp": {
      "real_total": 100,
      "true_positives": 3,
      "false_negative": 97,
      "false_positive": 83
    },
    "lawn_mower": {
      "real_total": 100,
      "true_positives": 21,
      "false_negative": 79,
      "false_positive": 63
    },
    "leopard": {
      "real_total": 100,
      "true_positives": 0,
      "false_negative": 100,
      "false_positive": 0
    },
    "lion": {
      "real_total": 100,
      "true_positives": 4,
      "false_negative": 96,
      "false_positive": 97
    },
    "lizard": {
      "real_total": 100,
      "true_positives": 2,
      "false_negative": 98,
      "false_positive": 134
    },
    "lobster": {
      "real_total": 100,
      "true_positives": 8,
      "false_negative": 92,
      "false_positive": 183
    },
    "man": {
      "real_total": 100,
      "true_positives": 0,
      "false_negative": 100,
      "false_positive": 0
    },
    "maple_tree": {
      "real_total": 100,
      "true_positives": 4,
      "false_negative": 96,
      "false_positive": 62
    },
    "motorcycle": {
      "real_total": 100,
      "true_positives": 8,
      "false_negative": 92,
      "false_positive": 64
    },
    "mountain": {
      "real_total": 100,
      "true_positives": 2,
      "false_negative": 98,
      "false_positive": 10
    },
    "mouse": {
      "real_total": 100,
      "true_positives": 1,
      "false_negative": 99,
      "false_positive": 39
    },
    "mushroom": {
      "real_total": 100,
      "true_positives": 3,
      "false_negative": 97,
      "false_positive": 84
    },
    "oak_tree": {
      "real_total": 100,
      "true_positives": 0,
      "false_negative": 100,
      "false_positive": 0
    },
    "orange": {
      "real_total": 100,
      "true_positives": 50,
      "false_negative": 50,
      "false_positive": 122
    },
    "orchid": {
      "real_total": 100,
      "true_positives": 21,
      "false_negative": 79,
      "false_positive": 165
    },
    "otter": {
      "real_total": 100,
      "true_positives": 0,
      "false_negative": 100,
      "false_positive": 48
    },
    "palm_tree": {
      "real_total": 100,
      "true_positives": 0,
      "false_negative": 100,
      "false_positive": 0
    },
    "pear": {
      "real_total": 100,
      "true_positives": 0,
      "false_negative": 100,
      "false_positive": 20
    },
    "pickup_truck": {
      "real_total": 100,
      "true_positives": 4,
      "false_negative": 96,
      "false_positive": 64
    },
    "pine_tree": {
      "real_total": 100,
      "true_positives": 3,
      "false_negative": 97,
      "false_positive": 103
    },
    "plain": {
      "real_total": 100,
      "true_positives": 23,
      "false_negative": 77,
      "false_positive": 252
    },
    "plate": {
      "real_total": 100,
      "true_positives": 12,
      "false_negative": 88,
      "false_positive": 257
    },
    "poppy": {
      "real_total": 100,
      "true_positives": 35,
      "false_negative": 65,
      "false_positive": 113
    },
    "porcupine": {
      "real_total": 100,
      "true_positives": 1,
      "false_negative": 99,
      "false_positive": 21
    },
    "possum": {
      "real_total": 100,
      "true_positives": 13,
      "false_negative": 87,
      "false_positive": 267
    },
    "rabbit": {
      "real_total": 100,
      "true_positives": 2,
      "false_negative": 98,
      "false_positive": 99
    },
    "raccoon": {
      "real_total": 100,
      "true_positives": 0,
      "false_negative": 100,
      "false_positive": 0
    },
    "ray": {
      "real_total": 100,
      "true_positives": 13,
      "false_negative": 87,
      "false_positive": 311
    },
    "road": {
      "real_total": 100,
      "true_positives": 0,
      "false_negative": 100,
      "false_positive": 0
    },
    "rocket": {
      "real_total": 100,
      "true_positives": 9,
      "false_negative": 91,
      "false_positive": 142
    },
    "rose": {
      "real_total": 100,
      "true_positives": 0,
      "false_negative": 100,
      "false_positive": 18
    },
    "sea": {
      "real_total": 100,
      "true_positives": 5,
      "false_negative": 95,
      "false_positive": 61
    },
    "seal": {
      "real_total": 100,
      "true_positives": 3,
      "false_negative": 97,
      "false_positive": 153
    },
    "shark": {
      "real_total": 100,
      "true_positives": 38,
      "false_negative": 62,
      "false_positive": 319
    },
    "shrew": {
      "real_total": 100,
      "true_positives": 6,
      "false_negative": 94,
      "false_positive": 166
    },
    "skunk": {
      "real_total": 100,
      "true_positives": 10,
      "false_negative": 90,
      "false_positive": 75
    },
    "skyscraper": {
      "real_total": 100,
      "true_positives": 5,
      "false_negative": 95,
      "false_positive": 32
    },
    "snail": {
      "real_total": 100,
      "true_positives": 0,
      "false_negative": 100,
      "false_positive": 117
    },
    "snake": {
      "real_total": 100,
      "true_positives": 6,
      "false_negative": 94,
      "false_positive": 117
    },
    "spider": {
      "real_total": 100,
      "true_positives": 0,
      "false_negative": 100,
      "false_positive": 0
    },
    "squirrel": {
      "real_total": 100,
      "true_positives": 7,
      "false_negative": 93,
      "false_positive": 142
    },
    "streetcar": {
      "real_total": 100,
      "true_positives": 7,
      "false_negative": 93,
      "false_positive": 144
    },
    "sunflower": {
      "real_total": 100,
      "true_positives": 5,
      "false_negative": 95,
      "false_positive": 104
    },
    "sweet_pepper": {
      "real_total": 100,
      "true_positives": 0,
      "false_negative": 100,
      "false_positive": 0
    },
    "table": {
      "real_total": 100,
      "true_positives": 1,
      "false_negative": 99,
      "false_positive": 60
    },
    "tank": {
      "real_total": 100,
      "true_positives": 8,
      "false_negative": 92,
      "false_positive": 166
    },
    "telephone": {
      "real_total": 100,
      "true_positives": 0,
      "false_negative": 100,
      "false_positive": 0
    },
    "television": {
      "real_total": 100,
      "true_positives": 7,
      "false_negative": 93,
      "false_positive": 170
    },
    "tiger": {
      "real_total": 100,
      "true_positives": 0,
      "false_negative": 100,
      "false_positive": 0
    },
    "tractor": {
      "real_total": 100,
      "true_positives": 4,
      "false_negative": 96,
      "false_positive": 100
    },
    "train": {
      "real_total": 100,
      "true_positives": 9,
      "false_negative": 91,
      "false_positive": 242
    },
    "trout": {
      "real_total": 100,
      "true_positives": 0,
      "false_negative": 100,
      "false_positive": 0
    },
    "tulip": {
      "real_total": 100,
      "true_positives": 5,
      "false_negative": 95,
      "false_positive": 136
    },
    "turtle": {
      "real_total": 100,
      "true_positives": 2,
      "false_negative": 98,
      "false_positive": 100
    },
    "wardrobe": {
      "real_total": 100,
      "true_positives": 25,
      "false_negative": 75,
      "false_positive": 136
    },
    "whale": {
      "real_total": 100,
      "true_positives": 10,
      "false_negative": 90,
      "false_positive": 99
    },
    "willow_tree": {
      "real_total": 100,
      "true_positives": 17,
      "false_negative": 83,
      "false_positive": 167
    },
    "wolf": {
      "real_total": 100,
      "true_positives": 5,
      "false_negative": 95,
      "false_positive": 218
    },
    "woman": {
      "real_total": 100,
      "true_positives": 1,
      "false_negative": 99,
      "false_positive": 88
    },
    "worm": {
      "real_total": 100,
      "true_positives": 16,
      "false_negative": 84,
      "false_positive": 307
    }
  },
  "per_class_accuracy": {
    "apple": 0.28,
    "aquarium_fish": 0.0,
    "baby": 0.01,
    "bear": 0.02,
    "beaver": 0.01,
    "bed": 0.02,
    "bee": 0.02,
    "beetle": 0.03,
    "bicycle": 0.08,
    "bottle": 0.04,
    "bowl": 0.02,
    "boy": 0.11,
    "bridge": 0.12,
    "bus": 0.0,
    "butterfly": 0.04,
    "camel": 0.13,
    "can": 0.1,
    "castle": 0.03,
    "caterpillar": 0.13,
    "cattle": 0.08,
    "chair": 0.18,
    "chimpanzee": 0.05,
    "clock": 0.02,
    "cloud": 0.17,
    "cockroach": 0.0,
    "couch": 0.03,
    "crab": 0.01,
    "crocodile": 0.0,
    "cup": 0.06,
    "dinosaur": 0.02,
    "dolphin": 0.03,
    "elephant": 0.0,
    "flatfish": 0.0,
    "forest": 0.0,
    "fox": 0.0,
    "girl": 0.0,
    "hamster": 0.02,
    "house": 0.06,
    "kangaroo": 0.07,
    "keyboard": 0.01,
    "lamp": 0.03,
    "lawn_mower": 0.21,
    "leopard": 0.0,
    "lion": 0.04,
    "lizard": 0.02,
    "lobster": 0.08,
    "man": 0.0,
    "maple_tree": 0.04,
    "motorcycle": 0.08,
    "mountain": 0.02,
    "mouse": 0.01,
    "mushroom": 0.03,
    "oak_tree": 0.0,
    "orange": 0.5,
    "orchid": 0.21,
    "otter": 0.0,
    "palm_tree": 0.0,
    "pear": 0.0,
    "pickup_truck": 0.04,
    "pine_tree": 0.03,
    "plain": 0.23,
    "plate": 0.12,
    "poppy": 0.35,
    "porcupine": 0.01,
    "possum": 0.13,
    "rabbit": 0.02,
    "raccoon": 0.0,
    "ray": 0.13,
    "road": 0.0,
    "rocket": 0.09,
    "rose": 0.0,
    "sea": 0.05,
    "seal": 0.03,
    "shark": 0.38,
    "shrew": 0.06,
    "skunk": 0.1,
    "skyscraper": 0.05,
    "snail": 0.0,
    "snake": 0.06,
    "spider": 0.0,
    "squirrel": 0.07,
    "streetcar": 0.07,
    "sunflower": 0.05,
    "sweet_pepper": 0.0,
    "table": 0.01,
    "tank": 0.08,
    "telephone": 0.0,
    "television": 0.07,
    "tiger": 0.0,
    "tractor": 0.04,
    "train": 0.09,
    "trout": 0.0,
    "tulip": 0.05,
    "turtle": 0.02,
    "wardrobe": 0.25,
    "whale": 0.1,
    "willow_tree": 0.17,
    "wolf": 0.05,
    "woman": 0.01,
    "worm": 0.16
  },
  "per_task_accuracy": {
    "0": 0.07450000000000001,
    "1": 0.058499999999999996,
    "2": 0.1035,
    "3": 0.0855,
    "4": 0.0
  }
}